MANIFEST.in
README.md
requirements.txt
setup.py
elsp_env.egg-info/PKG-INFO
elsp_env.egg-info/SOURCES.txt
elsp_env.egg-info/dependency_links.txt
elsp_env.egg-info/requires.txt
elsp_env.egg-info/top_level.txt
elsp_env_manager/__init__.py
elsp_env_manager/elsp_env.py
elsp_env_manager/eval_env.py
elsp_env_manager/base/__init__.py
elsp_env_manager/base/constants.py
elsp_env_manager/base/distribution.py
elsp_env_manager/base/m_id.py
elsp_env_manager/base/model_manager.py
elsp_env_manager/base/substance.py
elsp_env_manager/base/variables.py
elsp_env_manager/elsp_scheduling_rules/__init__.py
elsp_env_manager/elsp_scheduling_rules/bsp2/__init__.py
elsp_env_manager/elsp_scheduling_rules/bsp2/bsp2.py
elsp_env_manager/process/__init__.py
elsp_env_manager/process/process.py
elsp_env_manager/process_units/__init__.py
elsp_env_manager/process_units/process_line.py
elsp_env_manager/process_units/process_units.py
utils_minan/TimeCalculator.py
utils_minan/__init__.py