Metadata-Version: 1.0
Name: elsp-env
Version: 0.0.33
Summary: gym env elsp tool
Home-page: https://github.com/Meeea-914/elsp_env
Author: Meeea-914
Author-email: 1028634300@qq.com
License: MIT Licence
Keywords: pip,gymtool,envtool,elsptool,elsp
Platform: any
